MANIFEST.in
README.txt
VERSION.txt
setup.py
tox.ini
bbcu.rvcu.egg-info/PKG-INFO
bbcu.rvcu.egg-info/SOURCES.txt
bbcu.rvcu.egg-info/dependency_links.txt
bbcu.rvcu.egg-info/top_level.txt
rvcu/__init__.py
rvcu/agregate_mutations.bak.py
rvcu/agregate_mutations.py
rvcu/agregate_test.py
rvcu/base_distribution.py
rvcu/create_vcf.py
rvcu/extract_string.py
rvcu/filter_sam_junction_length.py
rvcu/filter_sam_pos_coverage.py
rvcu/sam_record.py
rvcu/utils.py
rvcu/utils_test.py
rvcu/test/__init__.py
scripts/__init__.py
scripts/divide_single_cell_bam.py
scripts/non_mutation_area.py
scripts/run-rvcu.py