Metadata-Version: 1.0
Name: bbcu.rvcu
Version: 1.0.1
Summary: Find RNA mutations and classify them by information form UMI (Unique Molecule Identifier)
Home-page: UNKNOWN
Author: Refael Kohen
Author-email: refael.kohen@weizmann.ac.il
License: UNKNOWN
Platform: UNKNOWN
